Workbook

Sheet Instrucciones
B2: MODELO ECONÓMICO · Propuesta del distribuidor de la costa del río Uruguay
B5: Qué es esto
B6: Un modelo para responder una sola pregunta: a qué markup y en qué condiciones esta operación deja de convenir. Todo está calculado con fórmulas: cambiás un supuesto y se recalcula solo.
B8: Estructura de precios que usa el modelo
B9: Todo se expresa como MARKUP SOBRE TU COSTO, que es como marcás vos. Compro a 100 y vendo a 112 = markup 12%. Los tres niveles cargados son: 15% directo a supermercado, 12% a tu mejor precio mayorista de hoy, y 10% que es lo que te dejaría este distribuidor.
B11: Cómo usarlo
B12: 1. Ir a 'Supuestos'. Las celdas AZULES sobre FONDO AMARILLO son las únicas editables.
B13: 2. Corregir los supuestos marcados como SUPUESTO, sobre todo el costo de servir (fila 24) y la facturación al resto de tus mayoristas (fila 36). Son los dos que más mueven el resultado.
B14: 3. 'Comparacion': cuánto gano hoy con estas bocas vs. cuánto ganaría con la propuesta.
B15: 4. 'Punto_Indiferencia': el markup mínimo que puedo aceptar, cuánto me deja la operación a precio mayorista pleno, y cuánto cobrar de fee si separo producto de servicio. Ese es el número que llevo a la reunión.
B16: 5. 'Riesgos': exposición de cobranza y el efecto contagio sobre el resto de la lista.
B17: 6. 'Sensibilidad': qué resultado da cada combinación de markup y costo de servir.
... B20: Azul sobre amarillo = dato que cargo yo | Negro = fórmula | Verde = viene de otra hoja

Sheet Supuestos
A1: SUPUESTOS
A2: Editar solo las celdas azules sobre fondo amarillo.
A4: 1. VOLUMEN Y BOCAS
A5: Cantidad de supermercados incluidos en la propuesta | B5: 5 | C5: Dato tuyo
A6: De esos, cuántos ya me compran directo hoy | B6: 2 | C6: SUPUESTO: dijiste 'algunos sí, otros no'. Ajustar.
A7: Volumen mensual de las 5 bocas, valuado a MI precio de venta directo ($/mes) | B7: 5000000 | C7: Dato tuyo: es lo que vos les facturarías.
A8: Volumen promedio por boca ($/mes) | B8: =B7/B5 -> 1000000
A9: Volumen que hoy ya facturo directo ($/mes) | B9: =B8*B6 -> 2000000
A10: Volumen incremental que sumaría ($/mes) | B10: =B7-B9 -> 3000000 | C10: Lo único realmente nuevo del negocio.
A12: 2. MÁRGENES (markup sobre mi costo: compro a 100, vendo a 100 x (1+markup))
A13: Markup vendiendo DIRECTO a supermercado | B13: 0.15 | C13: Dato tuyo.
A14: Markup de mi MEJOR precio mayorista hoy | B14: 0.12 | C14: Dato tuyo: el 12% que marcás como mejor precio.
A15: Markup que me dejaría ESTE distribuidor | B15: 0.1 | C15: Dato tuyo: 2 puntos por debajo del mejor mayorista.
A16: Costo de la mercadería de las 5 bocas ($/mes) | B16: =B7/(1+B13) -> 4347826.1
A17: Costo de la mercadería que hoy vendo directo ($/mes) | B17: =B9/(1+B13) -> 1739130.4
A18: Diferencia de markup vs. mi mejor mayorista (puntos) | B18: =B15-B14 -> -0.02
A19: Caída de precio implícita vs. mi precio mayorista | B19: =(1+B15)/(1+B14)-1 -> -0.017857143 | C19: Esto es lo que realmente le estoy bajando el precio. Es el número que se contagia al resto del book.
A21: 3. COSTO DE SERVIR (el trabajo lo sigo haciendo yo)
A22: Visitas + entregas por boca por mes | B22: 4 | C22: SUPUESTO: una por semana.
A23: Horas por visita (viaje, toma de pedido, armado, entrega, remito) | B23: 1.5 | C23: SUPUESTO. Cronometrar una semana real: es el parámetro que más mueve el resultado.
A24: Costo por hora cargado ($/h: sueldo + cargas, o mi propio tiempo) | B24: 7000 | C24: SUPUESTO CRÍTICO. Ajustar a tu costo real 2026.
A25: Costo fijo por boca por mes (combustible, vehículo, administración) ($) | B25: 8000 | C25: SUPUESTO.
A26: Costo de servir por boca por mes ($) | B26: =B22*B23*B24+B25 -> 50000
A27: Costo de servir las 5 bocas ($/mes) | B27: =B26*B5 -> 250000
A28: Costo de servir las bocas que ya atiendo hoy ($/mes) | B28: =B26*B6 -> 100000
A30: 4. FINANCIACIÓN Y COBRANZA
A31: Plazo de pago que propone el distribuidor (días) | B31: 15 | C31: Dato tuyo.
A32: Plazo de pago actual de los supermercados directos (días) | B32: 15 | C32: SUPUESTO: igual. Si hoy cobrás antes, bajarlo.
A33: Costo financiero mensual (%) | B33: 0.035 | C33: SUPUESTO. Usar tu costo real de capital.
A35: 5. RESTO DEL BOOK MAYORISTA (riesgo de contagio de precio)
A36: Facturación mensual a mis otros mayoristas y distribuidoras ($/mes) | B36: 15000000 | C36: SUPUESTO CRÍTICO. Poner tu número real: define si el contagio es tolerable o fatal.
A37: % de ese book que reclamaría paridad si se entera del precio | B37: 0.6 | C37: SUPUESTO. En una plaza chica la información circula.

Sheet Comparacion
A1: HOY vs. PROPUESTA · resultado mensual
A3: Concepto | B3: HOY (sin acuerdo) | C3: PROPUESTA (5 bocas vía distribuidor) | D3: Diferencia
A4: Bocas atendidas | B4: =Supuestos!B6 -> 2 | C4: =Supuestos!B5 -> 5 | D4: =C4-B4 -> 3
A5: Costo de la mercadería ($/mes) | B5: =Supuestos!B17 -> 1739130.4 | C5: =Supuestos!B16 -> 4347826.1 | D5: =C5-B5 -> 2608695.7
A6: Markup aplicado | B6: =Supuestos!B13 -> 0.15 | C6: =Supuestos!B15 -> 0.1 | D6: =C6-B6 -> -0.05
A7: Facturación ($/mes) | B7: =B5*(1+B6) -> 2000000 | C7: =C5*(1+C6) -> 4782608.7 | D7: =C7-B7 -> 2782608.7
A8: Margen bruto ($/mes) | B8: =B5*B6 -> 260869.57 | C8: =C5*C6 -> 434782.61 | D8: =C8-B8 -> 173913.04
A9: Margen bruto % sobre facturación | B9: =IF(B7=0,0,B8/B7) -> 0.13043478 | C9: =IF(C7=0,0,C8/C7) -> 0.090909091 | D9: =C9-B9 -> -0.039525692
A10: Costo de servir ($/mes) | B10: =Supuestos!B28 -> 100000 | C10: =Supuestos!B27 -> 250000 | D10: =C10-B10 -> 150000 | E10: Clave: el costo de servir NO baja. Sigo visitando, armando, entregando y presentando remitos igual que antes.
A11: Costo financiero del plazo ($/mes) | B11: =B7*Supuestos!$B$33*Supuestos!$B$32/30 -> 35000 | C11: =C7*Supuestos!$B$33*Supuestos!$B$31/30 -> 83695.652 | D11: =C11-B11 -> 48695.652
A12: RESULTADO OPERATIVO ($/mes) | B12: =B8-B10-B11 -> 125869.57 | C12: =C8-C10-C11 -> 101086.96 | D12: =C12-B12 -> -24782.609 | E12: <- Este es el número. Ojo: puede dar cerca de cero y aun así ser mal negocio, por lo que muestra la fila 16.
A13: Resultado anualizado ($) | B13: =B12*12 -> 1510434.8 | C13: =C12*12 -> 1213043.5 | D13: =D12*12 -> -297391.3
A15: Horas mías por mes en estas bocas | B15: =Supuestos!B6*Supuestos!B22*Supuestos!B23 -> 12 | C15: =Supuestos!B5*Supuestos!B22*Supuestos!B23 -> 30 | D15: =C15-B15 -> 18
A16: Resultado por hora trabajada ($/h) | B16: =IF(B15=0,0,B12/B15) -> 10489.13 | C16: =IF(C15=0,0,C12/C15) -> 3369.5652 | D16: =C16-B16 -> -7119.5652
A17: Margen bruto por hora trabajada ($/h) | B17: =IF(B15=0,0,B8/B15) -> 21739.13 | C17: =IF(C15=0,0,C8/C15) -> 14492.754 | D17: =C17-B17 -> -7246.3768 | E17: Test de escala: cuánto margen bruto genera cada hora que le dedico a estas bocas.

Sheet Punto_Indiferencia
A1: PUNTO DE INDIFERENCIA · el número que llevo a la reunión
A3: A. DATOS DE PARTIDA
A4: Resultado que hoy obtengo de estas bocas ($/mes) | B4: =Comparacion!B12 -> 125869.57
A5: Costo de servir las 5 bocas ($/mes) | B5: =Supuestos!B27 -> 250000
A6: Costo de la mercadería de las 5 bocas ($/mes) | B6: =Supuestos!B16 -> 4347826.1
A7: Plazo de pago (días) | B7: =Supuestos!B31 -> 15
A8: Costo financiero mensual (%) | B8: =Supuestos!B33 -> 0.035
A9: Costo financiero del período (tasa x días/30) | B9: =B8*B7/30 -> 0.0175
A11: B. MARKUP MÍNIMO QUE PUEDO ACEPTAR
A12: Markup mínimo al distribuidor | B12: =(B4+B5+B6*B9)/(B6*(1-B9)) -> 0.10580153 | C12: Markup al que la operación me deja exactamente lo mismo que gano hoy. Por debajo de esto, trabajo más para ganar menos.
A13: Markup que él ofrece | B13: =Supuestos!B15 -> 0.1
A14: Markup de mi mejor mayorista hoy | B14: =Supuestos!B14 -> 0.12
A15: BRECHA: lo que ofrece menos mi mínimo (puntos) | B15: =B13-B12 -> -0.0058015267
A16: Costo mensual de aceptar su markup ($/mes) | B16: =Comparacion!D12 -> -24782.609
A17: Costo anual de aceptar su markup ($) | B17: =B16*12 -> -297391.3
A19: C. QUÉ PASA SI LE COBRO MI PRECIO MAYORISTA PLENO (sin los 2 puntos)
A20: Facturación mensual ($) | B20: =B6*(1+Supuestos!B14) -> 4869565.2
A21: Margen bruto ($/mes) | B21: =B6*Supuestos!B14 -> 521739.13
A22: Costo de servir ($/mes) | B22: =B5 -> 250000
A23: Costo financiero ($/mes) | B23: =B20*B9 -> 85217.391
A24: Resultado ($/mes) | B24: =B21-B22-B23 -> 186521.74
A25: Diferencia contra lo que gano hoy ($/mes) | B25: =B24-B4 -> 60652.174 | C25: Si esto da positivo, el negocio SÍ conviene: lo que no conviene son los 2 puntos.
A27: D. ESTRUCTURA RECOMENDADA: producto a precio mayorista + servicio facturado aparte
A28: No toco la lista de precios (cero contagio) y cobro por separado el trabajo de reposición.
A29: Costo de servir las 5 bocas ($/mes) | B29: =B5 -> 250000
A30: Margen que quiero sobre el servicio (%) | B30: 0.25 | C30: Editable. Es un servicio, no una donación.
A31: FEE DE SERVICIO MENSUAL ($/mes) | B31: =B29*(1+B30) -> 312500
A32: Fee por boca por mes ($) | B32: =B31/Supuestos!B5 -> 62500 | C32: El número concreto para la mesa: 'el producto va a mi precio mayorista y la reposición la cobro a $X por boca por mes'.
A33: Fee por entrega ($) | B33: =B32/Supuestos!B22 -> 15625
A34: Fee como % de la facturación | B34: =IF(B20=0,0,B31/B20) -> 0.064174107
A35: Resultado total con esta estructura ($/mes) | B35: =B21+B31-B22-B23 -> 499021.74
A36: Diferencia contra lo que gano hoy ($/mes) | B36: =B35-B4 -> 373152.17

Sheet Riesgos
A1: COBRANZA, CONTAGIO DE PRECIO Y CONCENTRACIÓN
A3: A. EXPOSICIÓN DE COBRANZA
A4: Facturación mensual al distribuidor ($) | B4: =Comparacion!C7 -> 4782608.7
A5: Saldo expuesto a 15 días ($) | B5: =B4*Supuestos!B31/30 -> 2391304.3
A6: Saldo expuesto si estira a 30 días ($) | B6: =B4 -> 4782608.7 | C6: El plazo se estira después, no antes. Se acuerda a 15 días y a los 4 meses son 30. Para entonces ya perdí la relación directa con las bocas.
A7: Saldo expuesto si estira a 45 días ($) | B7: =B4*45/30 -> 7173913
A8: Saldo expuesto si estira a 60 días ($) | B8: =B4*2 -> 9565217.4
A9: Costo por cada 15 días de atraso ($/mes) | B9: =B4*Supuestos!B33*15/30 -> 83695.652
A11: B. CONTAGIO DE PRECIO AL RESTO DE LA LISTA
A12: Facturación mensual a otros mayoristas ($) | B12: =Supuestos!B36 -> 15000000
A13: % que reclamaría paridad | B13: =Supuestos!B37 -> 0.6
A14: Facturación expuesta al reclamo ($/mes) | B14: =B12*B13 -> 9000000
A15: Costo de esa mercadería ($/mes) | B15: =B14/(1+Supuestos!B14) -> 8035714.3
A16: Margen que gano hoy sobre lo expuesto ($/mes) | B16: =B15*Supuestos!B14 -> 964285.71
A17: Margen si tengo que alinear al nuevo markup ($/mes) | B17: =B15*Supuestos!B15 -> 803571.43
A18: PÉRDIDA POR CONTAGIO ($/mes) | B18: =B16-B17 -> 160714.29 | C18: Los 2 puntos no se pierden solo acá: se pierden en todo lo que después tenga que igualar. Y no vuelven.
A19: Pérdida por contagio anual ($) | B19: =B18*12 -> 1928571.4
A21: C. RESULTADO COMBINADO
A22: Efecto de la operación ($/mes) | B22: =Comparacion!D12 -> -24782.609
A23: Efecto del contagio ($/mes) | B23: =-B18 -> -160714.29
A24: EFECTO TOTAL SOBRE MI RESULTADO ($/mes) | B24: =B22+B23 -> -185496.89
A25: EFECTO TOTAL ANUAL ($) | B25: =B24*12 -> -2225962.7
A27: D. CONCENTRACIÓN Y DEPENDENCIA
A28: Facturación total mensual estimada ($) | B28: =Supuestos!B36+Comparacion!C7 -> 19782609
A29: % de mi facturación que pasaría por este cliente | B29: =IF(B28=0,0,Comparacion!C7/B28) -> 0.24175824 | C29: Arriba del 25% de concentración, el que fija las condiciones deja de ser el vendedor.
A30: Volumen que hoy facturo directo y quedaría en sus manos ($/mes) | B30: =Supuestos!B9 -> 2000000

Sheet Sensibilidad
A1: SENSIBILIDAD · Resultado mensual de la operación propuesta
A2: Filas: markup que me deja el distribuidor. Columnas: costo de servir por boca por mes.
A4: Markup al distribuidor | B4: 35000 | C4: 50000 | D4: 65000 | E4: 80000
A5: 0.13 | B5: =Supuestos!$B$16*$A5-Supuestos!$B$5*B$4-Supuestos!$B$16*(1+$A5)*Supuestos!$B$33*Supuestos!$B$31/30 -> 304239.13 | C5: =Supuestos!$B$16*$A5-Supuestos!$B$5*C$4-Supuestos!$B$16*(1+$A5)*Supuestos!$B$33*Supuestos!$B$31/30 -> 229239.13 | D5: =Supuestos!$B$16*$A5-Supuestos!$B$5*D$4-Supuestos!$B$16*(1+$A5)*Supuestos!$B$33*Supuestos!$B$31/30 -> 154239.13 | E5: =Supuestos!$B$16*$A5-Supuestos!$B$5*E$4-Supuestos!$B$16*(1+$A5)*Supuestos!$B$33*Supuestos!$B$31/30 -> 79239.13
A6: 0.12 | B6: =Supuestos!$B$16*$A6-Supuestos!$B$5*B$4-Supuestos!$B$16*(1+$A6)*Supuestos!$B$33*Supuestos!$B$31/30 -> 261521.74 | C6: =Supuestos!$B$16*$A6-Supuestos!$B$5*C$4-Supuestos!$B$16*(1+$A6)*Supuestos!$B$33*Supuestos!$B$31/30 -> 186521.74 | D6: =Supuestos!$B$16*$A6-Supuestos!$B$5*D$4-Supuestos!$B$16*(1+$A6)*Supuestos!$B$33*Supuestos!$B$31/30 -> 111521.74 | E6: =Supuestos!$B$16*$A6-Supuestos!$B$5*E$4-Supuestos!$B$16*(1+$A6)*Supuestos!$B$33*Supuestos!$B$31/30 -> 36521.739
A7: 0.115 | B7: =Supuestos!$B$16*$A7-Supuestos!$B$5*B$4-Supuestos!$B$16*(1+$A7)*Supuestos!$B$33*Supuestos!$B$31/30 -> 240163.04 | C7: =Supuestos!$B$16*$A7-Supuestos!$B$5*C$4-Supuestos!$B$16*(1+$A7)*Supuestos!$B$33*Supuestos!$B$31/30 -> 165163.04 | D7: =Supuestos!$B$16*$A7-Supuestos!$B$5*D$4-Supuestos!$B$16*(1+$A7)*Supuestos!$B$33*Supuestos!$B$31/30 -> 90163.043 | E7: =Supuestos!$B$16*$A7-Supuestos!$B$5*E$4-Supuestos!$B$16*(1+$A7)*Supuestos!$B$33*Supuestos!$B$31/30 -> 15163.043
A8: 0.11 | B8: =Supuestos!$B$16*$A8-Supuestos!$B$5*B$4-Supuestos!$B$16*(1+$A8)*Supuestos!$B$33*Supuestos!$B$31/30 -> 218804.35 | C8: =Supuestos!$B$16*$A8-Supuestos!$B$5*C$4-Supuestos!$B$16*(1+$A8)*Supuestos!$B$33*Supuestos!$B$31/30 -> 143804.35 | D8: =Supuestos!$B$16*$A8-Supuestos!$B$5*D$4-Supuestos!$B$16*(1+$A8)*Supuestos!$B$33*Supuestos!$B$31/30 -> 68804.348 | E8: =Supuestos!$B$16*$A8-Supuestos!$B$5*E$4-Supuestos!$B$16*(1+$A8)*Supuestos!$B$33*Supuestos!$B$31/30 -> -6195.6522
A9: 0.105 | B9: =Supuestos!$B$16*$A9-Supuestos!$B$5*B$4-Supuestos!$B$16*(1+$A9)*Supuestos!$B$33*Supuestos!$B$31/30 -> 197445.65 | C9: =Supuestos!$B$16*$A9-Supuestos!$B$5*C$4-Supuestos!$B$16*(1+$A9)*Supuestos!$B$33*Supuestos!$B$31/30 -> 122445.65 | D9: =Supuestos!$B$16*$A9-Supuestos!$B$5*D$4-Supuestos!$B$16*(1+$A9)*Supuestos!$B$33*Supuestos!$B$31/30 -> 47445.652 | E9: =Supuestos!$B$16*$A9-Supuestos!$B$5*E$4-Supuestos!$B$16*(1+$A9)*Supuestos!$B$33*Supuestos!$B$31/30 -> -27554.348
A10: 0.1 | B10: =Supuestos!$B$16*$A10-Supuestos!$B$5*B$4-Supuestos!$B$16*(1+$A10)*Supuestos!$B$33*Supuestos!$B$31/30 -> 176086.96 | C10: =Supuestos!$B$16*$A10-Supuestos!$B$5*C$4-Supuestos!$B$16*(1+$A10)*Supuestos!$B$33*Supuestos!$B$31/30 -> 101086.96 | D10: =Supuestos!$B$16*$A10-Supuestos!$B$5*D$4-Supuestos!$B$16*(1+$A10)*Supuestos!$B$33*Supuestos!$B$31/30 -> 26086.957 | E10: =Supuestos!$B$16*$A10-Supuestos!$B$5*E$4-Supuestos!$B$16*(1+$A10)*Supuestos!$B$33*Supuestos!$B$31/30 -> -48913.043
A11: 0.095 | B11: =Supuestos!$B$16*$A11-Supuestos!$B$5*B$4-Supuestos!$B$16*(1+$A11)*Supuestos!$B$33*Supuestos!$B$31/30 -> 154728.26 | C11: =Supuestos!$B$16*$A11-Supuestos!$B$5*C$4-Supuestos!$B$16*(1+$A11)*Supuestos!$B$33*Supuestos!$B$31/30 -> 79728.261 | D11: =Supuestos!$B$16*$A11-Supuestos!$B$5*D$4-Supuestos!$B$16*(1+$A11)*Supuestos!$B$33*Supuestos!$B$31/30 -> 4728.2609 | E11: =Supuestos!$B$16*$A11-Supuestos!$B$5*E$4-Supuestos!$B$16*(1+$A11)*Supuestos!$B$33*Supuestos!$B$31/30 -> -70271.739
A13: Referencias
A14: Markup que él ofrece | B14: =Supuestos!B15 -> 0.1 | F14: Toda celda de la tabla por debajo del valor de la fila 18 significa que la propuesta me deja peor que hoy.
A15: Mi markup mínimo aceptable | B15: =Punto_Indiferencia!B12 -> 0.10580153
A16: Markup de mi mejor mayorista hoy | B16: =Supuestos!B14 -> 0.12
A17: Costo de servir real por boca ($/mes) | B17: =Supuestos!B26 -> 50000
A18: Resultado que gano HOY con las bocas directas ($/mes) | B18: =Comparacion!B12 -> 125869.57
